key_people/.DS_Store
key_people/DB/.DS_Store
key_people/DB/Nicknames.db
key_people/DB/Stocks.db
key_people/__init__.py
key_people/database_management.py
key_people/generate_possible_names.py
key_people/key-people.py
key_people-0.932.dist-info/WHEEL
key_people-0.932.dist-info/METADATA
key_people-0.932.dist-info/RECORD
