Metadata-Version: 2.1
Name: key-people
Version: 0.932
Summary: This is used to pull any of the key people from a company based off of the ticker. Currently NASDAQ and NYSE supported
Home-page: https://github.com/BecketTrotter/Key_People
License: MIT
Keywords: stock,ticker,ceo,executives
Author: Henry Becket Trotter
Author-email: beckettrotter@gmail.com
Requires-Python: >=3.6,<4.0
Classifier: Environment :: Console
Classifier: License :: OSI Approved :: MIT License
Classifier: Operating System :: OS Independent
Classifier: Programming Language :: Python :: 3
Classifier: Programming Language :: Python :: 3.6
Classifier: Programming Language :: Python :: 3.7
Classifier: Programming Language :: Python :: 3.8
Classifier: Topic :: Software Development :: Documentation
Classifier: Topic :: Software Development :: Libraries :: Python Modules
Project-URL: Repository, https://github.com/BecketTrotter/Key_People
